dict_tools/__init__.py
dict_tools-0.3.0.dist-info/LICENSE
dict_tools-0.3.0.dist-info/METADATA
dict_tools-0.3.0.dist-info/WHEEL
dict_tools-0.3.0.dist-info/top_level.txt
dict_tools-0.3.0.dist-info/RECORD
