Metadata-Version: 2.1
Name: dict-tools
Version: 0.3.0
Summary: Utilities for dealing with dictionaries
Home-page: https://github.com/firba1/dict-tools
Author: Ben Bariteau
Author-email: ben.bariteau@gmail.com
License: MIT
Keywords: dictionaries
Platform: UNKNOWN
Classifier: Development Status :: 3 - Alpha
Classifier: License :: OSI Approved :: MIT License
Classifier: Programming Language :: Python :: 3
Classifier: Programming Language :: Python :: 3.6
Classifier: Programming Language :: Python :: 3.7
Classifier: Operating System :: OS Independent
Classifier: Topic :: Software Development :: Libraries :: Python Modules
